backlib/__init__.py
backlib/coolest-images-and-generators/bh_max.png
backlib/coolest-images-and-generators/bh_other.pdn
backlib/coolest-images-and-generators/black_hole.png
backlib/coolest-images-and-generators/black_hole_ultra_quality.png
backlib/coolest-images-and-generators/p_4096.png
backlib/coolest-images-and-generators/card_lab/fractal technology/graphic fractals/foo.svg
backlib/coolest-images-and-generators/card_lab/fractal technology/graphic fractals/mondel_2d.py
backlib/coolest-images-and-generators/card_lab/fractal technology/graphic fractals/tur.py
backlib/coolest-images-and-generators/card_lab/fractal technology/graphic fractals/apollonian gasket sets/base 3/ApollonianGasket.png
backlib/coolest-images-and-generators/card_lab/fractal technology/graphic fractals/apollonian gasket sets/base 3/apo_gasket.py
backlib/coolest-images-and-generators/card_lab/fractal technology/graphic fractals/apollonian gasket sets/base 4/ApollonianGasket.png
backlib/coolest-images-and-generators/card_lab/fractal technology/graphic fractals/apollonian gasket sets/base 4/apo_gasket.py
backlib/coolest-images-and-generators/card_lab/fractal technology/graphic fractals/apollonian gasket sets/base 6/ApollonianGasket.png
backlib/coolest-images-and-generators/card_lab/fractal technology/graphic fractals/apollonian gasket sets/base 6/apo_gasket.py
backlib/coolest-images-and-generators/card_lab/fractal technology/graphic fractals/apollonian gasket sets/base cbrt(64)/ApollonianGasket.png
backlib/coolest-images-and-generators/card_lab/fractal technology/graphic fractals/apollonian gasket sets/base cbrt(64)/apo_gasket.py
backlib/coolest-images-and-generators/card_lab/fractal technology/graphic fractals/apollonian gasket sets/base dynamic 2abs(z)/ApollonianGasket.png
backlib/coolest-images-and-generators/card_lab/fractal technology/graphic fractals/apollonian gasket sets/base dynamic 2abs(z)/apo_gasket.py
hyperpool-0.0.0.1.dist-info/METADATA
hyperpool-0.0.0.1.dist-info/WHEEL
hyperpool-0.0.0.1.dist-info/licenses/LICENSE
hyperpool-0.0.0.1.dist-info/RECORD
